pagerduty_auto_ack/__init__.py
pagerduty_auto_ack/cli.py
pagerduty_auto_ack/pd.py
pagerduty_auto_ack-1.0.0.dist-info/LICENSE
pagerduty_auto_ack-1.0.0.dist-info/METADATA
pagerduty_auto_ack-1.0.0.dist-info/WHEEL
pagerduty_auto_ack-1.0.0.dist-info/entry_points.txt
pagerduty_auto_ack-1.0.0.dist-info/RECORD
