Metadata-Version: 2.1
Name: pagerduty-auto-ack
Version: 1.0.0
Summary: Automatic acks for the PagerDuty incidents
Home-page: https://github.com/dezeroku/pagerduty-auto-ack
License: MIT
Author: dezeroku
Author-email: dezeroku@gmail.com
Requires-Python: >=3.11,<4.0
Classifier: License :: OSI Approved :: MIT License
Classifier: Programming Language :: Python :: 3
Classifier: Programming Language :: Python :: 3.11
Classifier: Programming Language :: Python :: 3.12
Requires-Dist: pdpyras (>=5.1.3,<6.0.0)
Project-URL: Repository, https://github.com/dezeroku/pagerduty-auto-ack
